ricecooker/__init__.py
ricecooker/chefs.py
ricecooker/commands.py
ricecooker/config.py
ricecooker/exceptions.py
ricecooker/classes/__init__.py
ricecooker/classes/files.py
ricecooker/classes/licenses.py
ricecooker/classes/nodes.py
ricecooker/classes/questions.py
ricecooker/managers/__init__.py
ricecooker/managers/progress.py
ricecooker/managers/tree.py
ricecooker/utils/__init__.py
ricecooker/utils/audio.py
ricecooker/utils/browser.py
ricecooker/utils/caching.py
ricecooker/utils/corrections.py
ricecooker/utils/downloader.py
ricecooker/utils/encodings.py
ricecooker/utils/html.py
ricecooker/utils/html_writer.py
ricecooker/utils/images.py
ricecooker/utils/jsontrees.py
ricecooker/utils/kolibripreview.py
ricecooker/utils/libstudio.py
ricecooker/utils/linecook.py
ricecooker/utils/metadata_provider.py
ricecooker/utils/paths.py
ricecooker/utils/pdf.py
ricecooker/utils/proxy.py
ricecooker/utils/request_utils.py
ricecooker/utils/slack.py
ricecooker/utils/subtitles.py
ricecooker/utils/thumbscropping.py
ricecooker/utils/tokens.py
ricecooker/utils/utils.py
ricecooker/utils/videos.py
ricecooker/utils/web.py
ricecooker/utils/youtube.py
ricecooker/utils/zip.py
ricecooker/utils/pipeline/__init__.py
ricecooker/utils/pipeline/context.py
ricecooker/utils/pipeline/convert.py
ricecooker/utils/pipeline/exceptions.py
ricecooker/utils/pipeline/extract_metadata.py
ricecooker/utils/pipeline/file_handler.py
ricecooker/utils/pipeline/transfer.py
ricecooker-0.8.0.dist-info/licenses/AUTHORS.rst
ricecooker-0.8.0.dist-info/licenses/LICENSE
ricecooker-0.8.0.dist-info/METADATA
ricecooker-0.8.0.dist-info/WHEEL
ricecooker-0.8.0.dist-info/entry_points.txt
ricecooker-0.8.0.dist-info/top_level.txt
ricecooker-0.8.0.dist-info/RECORD
