Metadata-Version: 2.4
Name: ricecooker
Version: 0.8.0
Summary: API for adding content to the Kolibri content curation server
Home-page: https://github.com/learningequality/ricecooker
Author: Learning Equality
Author-email: dev@learningequality.org
License: MIT license
Keywords: ricecooker
Classifier: Intended Audience :: Developers
Classifier: Development Status :: 5 - Production/Stable
Classifier: License :: OSI Approved :: MIT License
Classifier: Programming Language :: Python :: 3.9
Classifier: Programming Language :: Python :: 3.10
Classifier: Programming Language :: Python :: 3.11
Classifier: Programming Language :: Python :: 3.12
Classifier: Programming Language :: Python :: 3.13
Classifier: Natural Language :: English
Classifier: Topic :: Education
Requires-Python: >=3.9, <3.14
License-File: LICENSE
License-File: AUTHORS.rst
Requires-Dist: requests>=2.11.1
Requires-Dist: le_utils>=0.2.10
Requires-Dist: requests_file
Requires-Dist: beautifulsoup4<4.9.0,>=4.6.3
Requires-Dist: selenium==4.36.0
Requires-Dist: yt-dlp>=2024.12.23
Requires-Dist: html5lib
Requires-Dist: cachecontrol==0.14.3
Requires-Dist: filelock==3.19.1
Requires-Dist: css-html-js-minify==2.5.5
Requires-Dist: pypdf2==1.26.0
Requires-Dist: dictdiffer>=0.8.0
Requires-Dist: Pillow==11.3.0
Requires-Dist: colorlog<6.11,>=4.1.0
Requires-Dist: chardet==5.2.0
Requires-Dist: ffmpy>=0.2.2
Requires-Dist: pdf2image==1.17.0
Requires-Dist: le-pycaption>=2.2.0a1
Requires-Dist: EbookLib>=0.17.1
Requires-Dist: filetype>=1.1.0
Requires-Dist: urllib3==2.6.2
Requires-Dist: langcodes[data]==3.5.1
Provides-Extra: test
Requires-Dist: requests-cache==1.2.1; extra == "test"
Requires-Dist: pytest==8.4.2; extra == "test"
Requires-Dist: pytest-env==1.1.5; extra == "test"
Requires-Dist: vcrpy==7.0.0; python_version >= "3.10" and extra == "test"
Requires-Dist: mock==5.2.0; extra == "test"
Provides-Extra: dev
Requires-Dist: pre-commit>=4.1.0; extra == "dev"
Provides-Extra: google-drive
Requires-Dist: google-api-python-client; extra == "google-drive"
Requires-Dist: google-auth; extra == "google-drive"
Provides-Extra: sentry
Requires-Dist: sentry-sdk>=2.32.0; extra == "sentry"
Dynamic: author
Dynamic: author-email
Dynamic: classifier
Dynamic: description
Dynamic: description-content-type
Dynamic: home-page
Dynamic: keywords
Dynamic: license
Dynamic: license-file
Dynamic: provides-extra
Dynamic: requires-dist
Dynamic: requires-python
Dynamic: summary
